roblib/__init__.py
roblib/roblib.py
roblib-2.0.dist-info/METADATA
roblib-2.0.dist-info/WHEEL
roblib-2.0.dist-info/top_level.txt
roblib-2.0.dist-info/RECORD
